{
  "docid": "ekdTskHpS3WO",
  "source_url": "https://sudact.ru/regular/doc/ekdTskHpS3WO/",
  "source_domain": "sudact.ru",
  "source_title": "Решение № 2-477/2020 2-477/2020~М-466/2020... :: СудАкт.ру",
  "source_passage": "Согласно п. 1 ст. 18 Закона о защите прав потребителей в отношении технически сложного товара потребитель в случае обнаружения в нем недостатков вправе отказаться от исполнения договора купли-продажи и потребовать возврата уплаченной за такой товар суммы либо предъявить требование о его замене на товар этой же марки (модели, артикула) или на такой же товар другой марки (модели, артикула) с соответствующим перерасчетом покупной.",
  "raw_act_path": "data/raw_acts/act_ekdTskHpS3WO.txt",
  "raw_text_sha256": "ff821568be2c7dd2d9e779259a44eb0e6a35ea0bf37878869a31440a12b916c6",
  "source_type": "court_act",
  "metadata_updated_at": "2026-06-25T13:14:15+03:00"
}