{
  "docid": "hXJYppVEsNbO",
  "source_url": "https://sudact.ru/regular/doc/hXJYppVEsNbO/",
  "source_domain": "sudact.ru",
  "source_title": "Решение № 2-1161/2020 2-1161/2020~М-5989/2019... :: СудАкт.ру",
  "source_passage": "Согласно положениям ч. 2 ст. 9 Федерального закона от 30.12.2004 № 214-ФЗ «Об участии в долевом строительстве многоквартирных домов и иных объектов недвижимости и о внесении изменений в некоторые законодательные акты Российской Федерации» (далее - Федеральный закон от 30.12.2004 № 214-ФЗ) застройщик в случае расторжения договора по основаниям, предусмотренным частью 1 настоящей статьи, в течение двадцати рабочих дней.",
  "raw_act_path": "data/ddu/raw_acts/act_hXJYppVEsNbO.txt",
  "raw_text_sha256": "946138f1d73f9e9c150008244e368885a1db89203d2655162746156f7b6acfc8",
  "source_type": "court_act",
  "fetched_at": "2026-06-29T17:58:09+03:00"
}